Metadata-Version: 2.1
Name: spotify-cli
Version: 0.3.11
Summary: Control Spotify playback on any device through the command line.
Home-page: https://github.com/ledesmablt/spotify-cli
Author: Benj Ledesma
Author-email: benj.ledesma@gmail.com
License: MIT
Platform: UNKNOWN
Classifier: Programming Language :: Python :: 3
Classifier: License :: OSI Approved :: MIT License
Classifier: Operating System :: OS Independent
Requires-Python: >=3
License-File: LICENSE
Requires-Dist: Click
Requires-Dist: PyInquirer
Requires-Dist: tabulate
